arista/__init__.py
arista/action/__init__.py
arista/action/v1/__init__.py
arista/action/v1/action_pb2.py
arista/action/v1/action_pb2.pyi
arista/action/v1/action_pb2_grpc.py
arista/action/v1/services/__init__.py
arista/action/v1/services/gen_pb2.py
arista/action/v1/services/gen_pb2.pyi
arista/action/v1/services/gen_pb2_grpc.py
arista/alert/__init__.py
arista/alert/v1/__init__.py
arista/alert/v1/alert_pb2.py
arista/alert/v1/alert_pb2.pyi
arista/alert/v1/alert_pb2_grpc.py
arista/alert/v1/services/__init__.py
arista/alert/v1/services/gen_pb2.py
arista/alert/v1/services/gen_pb2.pyi
arista/alert/v1/services/gen_pb2_grpc.py
arista/auditlog/__init__.py
arista/auditlog/v1/__init__.py
arista/auditlog/v1/auditlog_pb2.py
arista/auditlog/v1/auditlog_pb2.pyi
arista/auditlog/v1/auditlog_pb2_grpc.py
arista/auditlog/v1/services/__init__.py
arista/auditlog/v1/services/gen_pb2.py
arista/auditlog/v1/services/gen_pb2.pyi
arista/auditlog/v1/services/gen_pb2_grpc.py
arista/bugexposure/__init__.py
arista/bugexposure/v1/__init__.py
arista/bugexposure/v1/bugexposure_pb2.py
arista/bugexposure/v1/bugexposure_pb2.pyi
arista/bugexposure/v1/bugexposure_pb2_grpc.py
arista/bugexposure/v1/services/__init__.py
arista/bugexposure/v1/services/gen_pb2.py
arista/bugexposure/v1/services/gen_pb2.pyi
arista/bugexposure/v1/services/gen_pb2_grpc.py
arista/changecontrol/__init__.py
arista/changecontrol/v1/__init__.py
arista/changecontrol/v1/changecontrol_pb2.py
arista/changecontrol/v1/changecontrol_pb2.pyi
arista/changecontrol/v1/changecontrol_pb2_grpc.py
arista/changecontrol/v1/services/__init__.py
arista/changecontrol/v1/services/gen_pb2.py
arista/changecontrol/v1/services/gen_pb2.pyi
arista/changecontrol/v1/services/gen_pb2_grpc.py
arista/configlet/__init__.py
arista/configlet/v1/__init__.py
arista/configlet/v1/configlet_pb2.py
arista/configlet/v1/configlet_pb2.pyi
arista/configlet/v1/configlet_pb2_grpc.py
arista/configlet/v1/services/__init__.py
arista/configlet/v1/services/gen_pb2.py
cloudvision-1.27.0.dist-info/COPYING
cloudvision-1.27.0.dist-info/METADATA
cloudvision-1.27.0.dist-info/WHEEL
cloudvision-1.27.0.dist-info/top_level.txt
cloudvision-1.27.0.dist-info/RECORD
