Metadata-Version: 2.1
Name: cloudvision
Version: 1.27.0
Summary: A Python library for Arista's CloudVision APIs and Provisioning Action integrations.
Maintainer-email: Support <support@arista.com>
Project-URL: Documentation, https://aristanetworks.github.io/cloudvision-python/
Project-URL: Source, https://github.com/aristanetworks/cloudvision-python
Classifier: License :: OSI Approved :: Apache Software License
Classifier: Programming Language :: Python :: 3
Classifier: Operating System :: OS Independent
Requires-Python: >=3.10.0
License-File: COPYING
Requires-Dist: aristaproto (==0.1.4)
Requires-Dist: cryptography (==46.0.3)
Requires-Dist: grpcio (>=1.53.0)
Requires-Dist: msgpack (>=1.0.3)
Requires-Dist: protobuf (<6.0dev,>=5.28.3)
Requires-Dist: pyavd-utils (==0.0.1)
Requires-Dist: requests (>=2.20.1)
Requires-Dist: typing-extensions (>=4.2.0)
Provides-Extra: dev
Requires-Dist: isort (==5.11.4) ; extra == 'dev'
Requires-Dist: black (==24.3.0) ; extra == 'dev'
Requires-Dist: mypy-protobuf (==3.6.0) ; extra == 'dev'
Requires-Dist: mypy (==0.981) ; extra == 'dev'
Requires-Dist: pytest (==8.3.4) ; extra == 'dev'
Requires-Dist: pytest-asyncio (==1.2.0) ; extra == 'dev'
Requires-Dist: numpy (==1.26.4) ; extra == 'dev'
Requires-Dist: pyyaml (==6.0.1) ; extra == 'dev'
Requires-Dist: flake8 (==7.3.0) ; extra == 'dev'
Requires-Dist: grpcio-tools (>=1.53.2) ; extra == 'dev'
Requires-Dist: twine (==4.0.1) ; extra == 'dev'
Requires-Dist: types-attrs (>=19.1.0) ; extra == 'dev'
Requires-Dist: types-protobuf (==5.29.1.20241207) ; extra == 'dev'
Requires-Dist: types-PyYAML (>=6.0.7) ; extra == 'dev'
Requires-Dist: types-requests (>=2.27.25) ; extra == 'dev'
Requires-Dist: types-setuptools (>=69.0.0.0) ; extra == 'dev'
Requires-Dist: wheel (==0.38.4) ; extra == 'dev'
